pyutils_dalofeco/Color.py
pyutils_dalofeco/Safe.py
pyutils_dalofeco/__init__.py
utils/Color.py
utils/Safe.py
utils/__init__.py
pyutils_dalofeco-0.1.dist-info/LICENSE
pyutils_dalofeco-0.1.dist-info/METADATA
pyutils_dalofeco-0.1.dist-info/WHEEL
pyutils_dalofeco-0.1.dist-info/top_level.txt
pyutils_dalofeco-0.1.dist-info/RECORD
