Metadata-Version: 2.1
Name: pyutils-dalofeco
Version: 0.1
Summary: Standard utility functions for Python 3+
Home-page: UNKNOWN
Author: Dalofeco
License: UNKNOWN
Platform: UNKNOWN
Classifier: Programming Language :: Python :: 3
Classifier: License :: OSI Approved :: MIT License
Classifier: Operating System :: OS Independent
Requires-Python: >=3.7
